lcp_pdf_mcp/__init__.py
lcp_pdf_mcp/pdf_utils.py
lcp_pdf_mcp/server.py
lcp_pdf_mcp-0.1.2.dist-info/METADATA
lcp_pdf_mcp-0.1.2.dist-info/WHEEL
lcp_pdf_mcp-0.1.2.dist-info/entry_points.txt
lcp_pdf_mcp-0.1.2.dist-info/RECORD
