Metadata-Version: 2.4
Name: lcp-pdf-mcp
Version: 0.1.2
Summary: 一個 MCP 伺服器，提供PDF分割與合併工具
Requires-Dist: fastmcp
Requires-Dist: pydantic
Requires-Dist: pypdf2
